crewai_tools/__init__.py
crewai_tools/adapters/embedchain_adapter.py
crewai_tools/adapters/lancedb_adapter.py
crewai_tools/adapters/pdf_embedchain_adapter.py
crewai_tools/tools/__init__.py
crewai_tools/tools/base_tool.py
crewai_tools/tools/browserbase_load_tool/README.md
crewai_tools/tools/browserbase_load_tool/browserbase_load_tool.py
crewai_tools/tools/code_docs_search_tool/README.md
crewai_tools/tools/code_docs_search_tool/code_docs_search_tool.py
crewai_tools/tools/code_interpreter_tool/Dockerfile
crewai_tools/tools/code_interpreter_tool/README.md
crewai_tools/tools/code_interpreter_tool/code_interpreter_tool.py
crewai_tools/tools/composio_tool/README.md
crewai_tools/tools/composio_tool/composio_tool.py
crewai_tools/tools/csv_search_tool/README.md
crewai_tools/tools/csv_search_tool/csv_search_tool.py
crewai_tools/tools/directory_read_tool/README.md
crewai_tools/tools/directory_read_tool/directory_read_tool.py
crewai_tools/tools/directory_search_tool/README.md
crewai_tools/tools/directory_search_tool/directory_search_tool.py
crewai_tools/tools/docx_search_tool/README.md
crewai_tools/tools/docx_search_tool/docx_search_tool.py
crewai_tools/tools/exa_tools/README.md
crewai_tools/tools/exa_tools/exa_base_tool.py
crewai_tools/tools/exa_tools/exa_search_tool.py
crewai_tools/tools/file_read_tool/README.md
crewai_tools/tools/file_read_tool/file_read_tool.py
crewai_tools/tools/firecrawl_crawl_website_tool/README.md
crewai_tools/tools/firecrawl_crawl_website_tool/firecrawl_crawl_website_tool.py
crewai_tools/tools/firecrawl_scrape_website_tool/README.md
crewai_tools/tools/firecrawl_scrape_website_tool/firecrawl_scrape_website_tool.py
crewai_tools/tools/firecrawl_search_tool/README.md
crewai_tools/tools/firecrawl_search_tool/firecrawl_search_tool.py
crewai_tools/tools/github_search_tool/README.md
crewai_tools/tools/github_search_tool/github_search_tool.py
crewai_tools/tools/json_search_tool/README.md
crewai_tools/tools/json_search_tool/json_search_tool.py
aipmai_tools-0.4.26.dist-info/LICENSE
aipmai_tools-0.4.26.dist-info/METADATA
aipmai_tools-0.4.26.dist-info/WHEEL
aipmai_tools-0.4.26.dist-info/RECORD
